idlib/__init__.py
idlib/auth-config.py
idlib/cache.py
idlib/config.py
idlib/core.py
idlib/edit.py
idlib/exceptions.py
idlib/from_oq.py
idlib/identifiers.py
idlib/streams.py
idlib/utils.py
idlib/apis/__init__.py
idlib/apis/protocols_io.py
idlib/conventions/__init__.py
idlib/conventions/core.py
idlib/conventions/local.py
idlib/conventions/type.py
idlib/formats/__init__.py
idlib/formats/rdf.py
idlib/systems/__init__.py
idlib/systems/ark.py
idlib/systems/doi.py
idlib/systems/handle.py
idlib/systems/isni.py
idlib/systems/orcid.py
idlib/systems/pmid.py
idlib/systems/ror.py
idlib/systems/rrid.py
idlib/systems/urn.py
idlib/systems/web.py
idlib-0.0.1.dev23.dist-info/licenses/LICENSE
idlib-0.0.1.dev23.dist-info/METADATA
idlib-0.0.1.dev23.dist-info/WHEEL
idlib-0.0.1.dev23.dist-info/top_level.txt
idlib-0.0.1.dev23.dist-info/RECORD
